Full_adder/full_adder.v
module full_adder(A,B,C,sum,carry);
    input A,B,C;
    output sum,carry;
    assign sum=(A^B^C);
    assign carry=(A&B)|(B&C)|(A&C);
endmodule

Full_adder/full_adder_tb.v
`timescale 1ns/1ps
module full_adder_tb();
    reg t_a,t_b,t_c;
    wire t_s,t_cout;

    full_adder gut(
        .A(t_a), .B(t_b), .C(t_c), .sum(t_s), .carry(t_cout)
    );

    initial begin
        //generate waveform
        $dumpfile("full_adder.vcd");
        $dumpvars(0,full_adder_tb);

        $display("A|B|C|Sum|Carry");
        // Case-1
        t_a=0; t_b=0; t_c=0;
        #10;
        $display("%b %b %b | %b %b",t_a,t_b,t_c,t_s,t_cout);
        // Case-2
        t_a=0; t_b=0; t_c=1;
        #10;
        $display("%b %b %b | %b %b",t_a,t_b,t_c,t_s,t_cout);
        // Case-3
        t_a=0; t_b=1; t_c=0;
        #10;
        $display("%b %b %b | %b %b",t_a,t_b,t_c,t_s,t_cout);
        // Case-4
        t_a=0; t_b=1; t_c=1;
        #10;
        $display("%b %b %b | %b %b",t_a,t_b,t_c,t_s,t_cout);
        // Case-5
        t_a=1; t_b=0; t_c=0;
        #10;
        $display("%b %b %b | %b %b",t_a,t_b,t_c,t_s,t_cout);
        // Case-6
        t_a=1; t_b=0; t_c=1;
        #10;
        $display("%b %b %b | %b %b",t_a,t_b,t_c,t_s,t_cout);
        // Case-7
        t_a=1; t_b=1; t_c=0;
        #10;
        $display("%b %b %b | %b %b",t_a,t_b,t_c,t_s,t_cout);
        // Case-8
        t_a=1; t_b=1; t_c=1;
        #10;
        $display("%b %b %b | %b %b",t_a,t_b,t_c,t_s,t_cout);
        $finish;
    end 
endmodule

Full_adder/full_adder.vcd
$date
	Tue Feb 24 10:32:43 2026
$end
$version
	Icarus Verilog
$end
$timescale
	1ps
$end
$scope module full_adder_tb $end
$var wire 1 ! t_s $end
$var wire 1 " t_cout $end
$var reg 1 # t_a $end
$var reg 1 $ t_b $end
$var reg 1 % t_c $end
$scope module gut $end
$var wire 1 # A $end
$var wire 1 $ B $end
$var wire 1 % C $end
$var wire 1 " carry $end
$var wire 1 ! sum $end
$upscope $end
$upscope $end
$enddefinitions $end
$comment Show the parameter values. $end
$dumpall
$end
#0
$dumpvars
0%
0$
0#
0"
0!
$end
#10000
1!
1%
#20000
0%
1$
#30000
1"
0!
1%
#40000
0"
1!
0%
0$
1#
#50000
1"
0!
1%
#60000
0%
1$
#70000
1!
1%
